{
  "updated_at": "2026-07-13 23:56:02",
  "total_scanned": 2061,
  "stats": {
    "us_count": 502,
    "jp_count": 1559,
    "avg_score_us": 5.22,
    "avg_score_jp": 3.96
  },
  "usdjpy": 162.44,
  "ranking": [
    {
      "rank": 1,
      "ticker": "285A.T",
      "name": "キオクシアホールディングス",
      "market": "JP",
      "currency": "JPY",
      "price": 67100.0,
      "day_chg": -12.86,
      "ret_1m": -26.19,
      "ret_3m": 122.63,
      "ret_6m": 428.76,
      "ret_1y": 2653.39,
      "ytd_chg": 491.19,
      "rsi": 33.6,
      "from_ath": -38.27,
      "vol_ratio": 1.22,
      "volatility": 0.083,
      "score": 112.06,
      "ma5": 73246.0,
      "ma20": 87969.0,
      "ma50": 71742.0,
      "high_52w": 108700.0,
      "low_52w": 2300.0
    },
    {
      "rank": 2,
      "ticker": "4392.T",
      "name": "ＦＩＧ",
      "market": "JP",
      "currency": "JPY",
      "price": 1051.0,
      "day_chg": -3.58,
      "ret_1m": -20.2,
      "ret_3m": 226.4,
      "ret_6m": 252.68,
      "ret_1y": 288.08,
      "ytd_chg": 268.77,
      "rsi": 42.3,
      "from_ath": -59.12,
      "vol_ratio": 0.76,
      "volatility": 0.043,
      "score": 110.38,
      "ma5": 1079.4,
      "ma20": 1144.75,
      "ma50": 1272.46,
      "high_52w": 2571.0,
      "low_52w": 266.95
    },
    {
      "rank": 3,
      "ticker": "3436.T",
      "name": "ＳＵＭＣＯ",
      "market": "JP",
      "currency": "JPY",
      "price": 5133.0,
      "day_chg": -2.12,
      "ret_1m": 19.55,
      "ret_3m": 153.08,
      "ret_6m": 230.75,
      "ret_1y": 342.39,
      "ytd_chg": 255.17,
      "rsi": 69.3,
      "from_ath": -2.12,
      "vol_ratio": 2.35,
      "volatility": 0.071,
      "score": 99.89,
      "ma5": 4799.6,
      "ma20": 4379.85,
      "ma50": 3841.69,
      "high_52w": 5244.0,
      "low_52w": 1147.41
    },
    {
      "rank": 4,
      "ticker": "DELL",
      "name": "Dell Technologies Inc.",
      "market": "US",
      "currency": "USD",
      "price": 427.11,
      "day_chg": -1.81,
      "ret_1m": 9.11,
      "ret_3m": 125.74,
      "ret_6m": 256.75,
      "ret_1y": 245.03,
      "ytd_chg": 236.7,
      "rsi": 52.1,
      "from_ath": -8.34,
      "vol_ratio": 0.52,
      "volatility": 0.035,
      "score": 92.71,
      "ma5": 432.31,
      "ma20": 418.3,
      "ma50": 349.15,
      "high_52w": 465.96,
      "low_52w": 110.73
    },
    {
      "rank": 5,
      "ticker": "SNDK",
      "name": "Sandisk Corporation",
      "market": "US",
      "currency": "USD",
      "price": 1673.97,
      "day_chg": -12.63,
      "ret_1m": -11.03,
      "ret_3m": 75.74,
      "ret_6m": 343.54,
      "ret_1y": 3840.61,
      "ytd_chg": 508.19,
      "rsi": 37.9,
      "from_ath": -28.31,
      "vol_ratio": 1.13,
      "volatility": 0.097,
      "score": 87.02,
      "ma5": 1758.61,
      "ma20": 1971.97,
      "ma50": 1700.44,
      "high_52w": 2335.0,
      "low_52w": 40.69
    },
    {
      "rank": 6,
      "ticker": "6976.T",
      "name": "太陽誘電",
      "market": "JP",
      "currency": "JPY",
      "price": 11900.0,
      "day_chg": -19.21,
      "ret_1m": -38.29,
      "ret_3m": 140.06,
      "ret_6m": 231.81,
      "ret_1y": 376.4,
      "ytd_chg": 227.56,
      "rsi": 38.0,
      "from_ath": -47.47,
      "vol_ratio": 1.12,
      "volatility": 0.087,
      "score": 73.06,
      "ma5": 14526.0,
      "ma20": 18030.25,
      "ma50": 14043.82,
      "high_52w": 22655.0,
      "low_52w": 2481.32
    },
    {
      "rank": 7,
      "ticker": "AMD",
      "name": "Advanced Micro Devices, Inc.",
      "market": "US",
      "currency": "USD",
      "price": 534.39,
      "day_chg": -4.21,
      "ret_1m": 9.41,
      "ret_3m": 116.5,
      "ret_6m": 163.03,
      "ret_1y": 265.42,
      "ytd_chg": 139.13,
      "rsi": 47.3,
      "from_ath": -8.01,
      "vol_ratio": 0.75,
      "volatility": 0.05,
      "score": 71.32,
      "ma5": 534.5,
      "ma20": 533.25,
      "ma50": 485.84,
      "high_52w": 580.91,
      "low_52w": 146.24
    },
    {
      "rank": 8,
      "ticker": "6779.T",
      "name": "日本電波工業",
      "market": "JP",
      "currency": "JPY",
      "price": 3200.0,
      "day_chg": -4.33,
      "ret_1m": -16.23,
      "ret_3m": 115.63,
      "ret_6m": 212.82,
      "ret_1y": 342.78,
      "ytd_chg": 220.24,
      "rsi": 33.0,
      "from_ath": -33.75,
      "vol_ratio": 0.41,
      "volatility": 0.064,
      "score": 70.76,
      "ma5": 3225.0,
      "ma20": 3778.25,
      "ma50": 3350.9,
      "high_52w": 4830.0,
      "low_52w": 722.71
    },
    {
      "rank": 9,
      "ticker": "MU",
      "name": "Micron Technology, Inc.",
      "market": "US",
      "currency": "USD",
      "price": 937.0,
      "day_chg": -4.32,
      "ret_1m": -5.9,
      "ret_3m": 119.7,
      "ret_6m": 171.68,
      "ret_1y": 691.25,
      "ytd_chg": 197.23,
      "rsi": 32.3,
      "from_ath": -22.78,
      "vol_ratio": 0.67,
      "volatility": 0.071,
      "score": 67.89,
      "ma5": 959.02,
      "ma20": 1050.5,
      "ma50": 907.3,
      "high_52w": 1213.37,
      "low_52w": 104.71
    },
    {
      "rank": 10,
      "ticker": "DDOG",
      "name": "Datadog, Inc.",
      "market": "US",
      "currency": "USD",
      "price": 260.24,
      "day_chg": 1.05,
      "ret_1m": 11.1,
      "ret_3m": 136.41,
      "ret_6m": 107.38,
      "ret_1y": 87.49,
      "ytd_chg": 94.54,
      "rsi": 72.9,
      "from_ath": -6.22,
      "vol_ratio": 0.83,
      "volatility": 0.029,
      "score": 66.84,
      "ma5": 260.94,
      "ma20": 243.14,
      "ma50": 223.38,
      "high_52w": 277.49,
      "low_52w": 102.61
    },
    {
      "rank": 11,
      "ticker": "6981.T",
      "name": "村田製作所",
      "market": "JP",
      "currency": "JPY",
      "price": 9066.0,
      "day_chg": -8.05,
      "ret_1m": -9.88,
      "ret_3m": 118.67,
      "ret_6m": 173.92,
      "ret_1y": 335.62,
      "ytd_chg": 174.82,
      "rsi": 37.8,
      "from_ath": -25.99,
      "vol_ratio": 1.23,
      "volatility": 0.063,
      "score": 66.43,
      "ma5": 9328.0,
      "ma20": 10732.0,
      "ma50": 8935.68,
      "high_52w": 12250.0,
      "low_52w": 2081.17
    },
    {
      "rank": 12,
      "ticker": "6266.T",
      "name": "タツモ",
      "market": "JP",
      "currency": "JPY",
      "price": 5090.0,
      "day_chg": -2.3,
      "ret_1m": 21.92,
      "ret_3m": 97.52,
      "ret_6m": 130.84,
      "ret_1y": 133.53,
      "ytd_chg": 145.89,
      "rsi": 54.8,
      "from_ath": -2.3,
      "vol_ratio": 1.83,
      "volatility": 0.057,
      "score": 64.19,
      "ma5": 4808.0,
      "ma20": 4704.0,
      "ma50": 4050.18,
      "high_52w": 5210.0,
      "low_52w": 1860.77
    },
    {
      "rank": 13,
      "ticker": "3480.T",
      "name": "ジェイ・エス・ビー",
      "market": "JP",
      "currency": "JPY",
      "price": 8990.0,
      "day_chg": 0.0,
      "ret_1m": 13.37,
      "ret_3m": 70.91,
      "ret_6m": 160.96,
      "ret_1y": 137.55,
      "ytd_chg": 159.45,
      "rsi": 50.0,
      "from_ath": 0.0,
      "vol_ratio": 0.13,
      "volatility": 0.03,
      "score": 58.81,
      "ma5": 8986.0,
      "ma20": 8980.5,
      "ma50": 7308.0,
      "high_52w": 8990.0,
      "low_52w": 3200.0
    },
    {
      "rank": 14,
      "ticker": "6480.T",
      "name": "日本トムソン",
      "market": "JP",
      "currency": "JPY",
      "price": 2013.0,
      "day_chg": -3.03,
      "ret_1m": 1.21,
      "ret_3m": 102.52,
      "ret_6m": 137.62,
      "ret_1y": 257.32,
      "ytd_chg": 147.98,
      "rsi": 33.6,
      "from_ath": -21.98,
      "vol_ratio": 0.81,
      "volatility": 0.062,
      "score": 58.76,
      "ma5": 2016.4,
      "ma20": 2208.75,
      "ma50": 2011.02,
      "high_52w": 2580.0,
      "low_52w": 543.14
    },
    {
      "rank": 15,
      "ticker": "6101.T",
      "name": "ツガミ",
      "market": "JP",
      "currency": "JPY",
      "price": 7490.0,
      "day_chg": -4.1,
      "ret_1m": 4.9,
      "ret_3m": 76.65,
      "ret_6m": 163.32,
      "ret_1y": 312.33,
      "ytd_chg": 163.41,
      "rsi": 49.3,
      "from_ath": -8.44,
      "vol_ratio": 1.08,
      "volatility": 0.046,
      "score": 57.62,
      "ma5": 7412.0,
      "ma20": 7647.5,
      "ma50": 6714.9,
      "high_52w": 8180.0,
      "low_52w": 1783.48
    },
    {
      "rank": 16,
      "ticker": "STX",
      "name": "Seagate Technology Holdings PLC",
      "market": "US",
      "currency": "USD",
      "price": 860.66,
      "day_chg": -5.46,
      "ret_1m": -0.79,
      "ret_3m": 67.8,
      "ret_6m": 183.8,
      "ret_1y": 482.08,
      "ytd_chg": 200.05,
      "rsi": 33.3,
      "from_ath": -21.28,
      "vol_ratio": 0.79,
      "volatility": 0.06,
      "score": 56.79,
      "ma5": 869.75,
      "ma20": 952.47,
      "ma50": 872.64,
      "high_52w": 1093.26,
      "low_52w": 145.39
    },
    {
      "rank": 17,
      "ticker": "FTNT",
      "name": "Fortinet, Inc.",
      "market": "US",
      "currency": "USD",
      "price": 160.62,
      "day_chg": 1.97,
      "ret_1m": 10.73,
      "ret_3m": 103.99,
      "ret_6m": 102.75,
      "ret_1y": 55.99,
      "ytd_chg": 106.24,
      "rsi": 64.2,
      "from_ath": -1.9,
      "vol_ratio": 0.65,
      "volatility": 0.024,
      "score": 56.04,
      "ma5": 159.45,
      "ma20": 152.77,
      "ma50": 135.76,
      "high_52w": 163.73,
      "low_52w": 74.39
    },
    {
      "rank": 18,
      "ticker": "WDC",
      "name": "Western Digital Corporation",
      "market": "US",
      "currency": "USD",
      "price": 555.55,
      "day_chg": -4.64,
      "ret_1m": 4.96,
      "ret_3m": 58.7,
      "ret_6m": 177.34,
      "ret_1y": 732.3,
      "ytd_chg": 196.2,
      "rsi": 33.9,
      "from_ath": -25.55,
      "vol_ratio": 0.45,
      "volatility": 0.075,
      "score": 55.06,
      "ma5": 559.72,
      "ma20": 623.45,
      "ma50": 549.07,
      "high_52w": 746.23,
      "low_52w": 66.35
    },
    {
      "rank": 19,
      "ticker": "6997.T",
      "name": "日本ケミコン",
      "market": "JP",
      "currency": "JPY",
      "price": 3655.0,
      "day_chg": -7.82,
      "ret_1m": -23.7,
      "ret_3m": 120.18,
      "ret_6m": 142.06,
      "ret_1y": 225.37,
      "ytd_chg": 146.57,
      "rsi": 31.3,
      "from_ath": -38.88,
      "vol_ratio": 0.89,
      "volatility": 0.08,
      "score": 54.99,
      "ma5": 3942.0,
      "ma20": 5068.5,
      "ma50": 4342.8,
      "high_52w": 5980.0,
      "low_52w": 1123.33
    },
    {
      "rank": 20,
      "ticker": "PANW",
      "name": "Palo Alto Networks, Inc.",
      "market": "US",
      "currency": "USD",
      "price": 330.3,
      "day_chg": 1.35,
      "ret_1m": 18.16,
      "ret_3m": 103.25,
      "ret_6m": 74.74,
      "ret_1y": 73.19,
      "ytd_chg": 84.14,
      "rsi": 63.6,
      "from_ath": -7.62,
      "vol_ratio": 0.71,
      "volatility": 0.035,
      "score": 53.19,
      "ma5": 330.43,
      "ma20": 312.83,
      "ma50": 270.07,
      "high_52w": 357.53,
      "low_52w": 141.67
    },
    {
      "rank": 21,
      "ticker": "7735.T",
      "name": "ＳＣＲＥＥＮホールディングス",
      "market": "JP",
      "currency": "JPY",
      "price": 17755.0,
      "day_chg": -2.18,
      "ret_1m": 19.48,
      "ret_3m": 65.24,
      "ret_6m": 124.07,
      "ret_1y": 205.91,
      "ytd_chg": 123.93,
      "rsi": 56.9,
      "from_ath": -8.9,
      "vol_ratio": 0.72,
      "volatility": 0.051,
      "score": 52.18,
      "ma5": 17527.0,
      "ma20": 17173.0,
      "ma50": 13870.3,
      "high_52w": 19490.0,
      "low_52w": 5241.8
    },
    {
      "rank": 22,
      "ticker": "4062.T",
      "name": "イビデン",
      "market": "JP",
      "currency": "JPY",
      "price": 18690.0,
      "day_chg": -7.93,
      "ret_1m": -17.85,
      "ret_3m": 89.02,
      "ret_6m": 159.26,
      "ret_1y": 506.03,
      "ytd_chg": 161.58,
      "rsi": 32.5,
      "from_ath": -29.27,
      "vol_ratio": 0.84,
      "volatility": 0.062,
      "score": 51.42,
      "ma5": 19501.0,
      "ma20": 23082.25,
      "ma50": 20159.2,
      "high_52w": 26425.0,
      "low_52w": 3056.16
    },
    {
      "rank": 23,
      "ticker": "HPE",
      "name": "Hewlett Packard Enterprise Comp",
      "market": "US",
      "currency": "USD",
      "price": 47.24,
      "day_chg": -2.68,
      "ret_1m": 1.24,
      "ret_3m": 90.96,
      "ret_6m": 115.08,
      "ret_1y": 133.3,
      "ytd_chg": 97.28,
      "rsi": 47.2,
      "from_ath": -15.62,
      "vol_ratio": 0.66,
      "volatility": 0.037,
      "score": 50.8,
      "ma5": 46.61,
      "ma20": 46.41,
      "ma50": 41.44,
      "high_52w": 55.99,
      "low_52w": 19.41
    },
    {
      "rank": 24,
      "ticker": "6237.T",
      "name": "イワキポンプ",
      "market": "JP",
      "currency": "JPY",
      "price": 4525.0,
      "day_chg": 0.44,
      "ret_1m": 38.38,
      "ret_3m": 63.71,
      "ret_6m": 75.75,
      "ret_1y": 82.32,
      "ytd_chg": 76.49,
      "rsi": 86.4,
      "from_ath": 0.0,
      "vol_ratio": 1.26,
      "volatility": 0.028,
      "score": 49.62,
      "ma5": 4358.0,
      "ma20": 3846.75,
      "ma50": 3384.68,
      "high_52w": 4525.0,
      "low_52w": 2317.68
    },
    {
      "rank": 25,
      "ticker": "6324.T",
      "name": "ハーモニック・ドライブ・システムズ",
      "market": "JP",
      "currency": "JPY",
      "price": 7240.0,
      "day_chg": -8.12,
      "ret_1m": 5.54,
      "ret_3m": 81.45,
      "ret_6m": 102.45,
      "ret_1y": 184.35,
      "ytd_chg": 89.01,
      "rsi": 45.6,
      "from_ath": -18.56,
      "vol_ratio": 0.96,
      "volatility": 0.07,
      "score": 47.14,
      "ma5": 7632.0,
      "ma20": 7828.5,
      "ma50": 7202.2,
      "high_52w": 8890.0,
      "low_52w": 2313.64
    },
    {
      "rank": 26,
      "ticker": "3445.T",
      "name": "ＲＳ　Ｔｅｃｈｎｏｌｏｇｉｅｓ",
      "market": "JP",
      "currency": "JPY",
      "price": 7600.0,
      "day_chg": -4.16,
      "ret_1m": 8.73,
      "ret_3m": 77.16,
      "ret_6m": 101.06,
      "ret_1y": 161.94,
      "ytd_chg": 96.89,
      "rsi": 54.8,
      "from_ath": -10.06,
      "vol_ratio": 1.11,
      "volatility": 0.052,
      "score": 46.85,
      "ma5": 7952.0,
      "ma20": 7475.5,
      "ma50": 7099.2,
      "high_52w": 8450.0,
      "low_52w": 2885.6
    },
    {
      "rank": 27,
      "ticker": "7717.T",
      "name": "ブイ・テクノロジー",
      "market": "JP",
      "currency": "JPY",
      "price": 7180.0,
      "day_chg": 1.84,
      "ret_1m": 13.25,
      "ret_3m": 49.58,
      "ret_6m": 132.92,
      "ret_1y": 151.88,
      "ytd_chg": 131.81,
      "rsi": 42.2,
      "from_ath": -23.45,
      "vol_ratio": 0.88,
      "volatility": 0.068,
      "score": 46.76,
      "ma5": 6860.0,
      "ma20": 7878.5,
      "ma50": 6449.6,
      "high_52w": 9380.0,
      "low_52w": 2772.25
    },
    {
      "rank": 28,
      "ticker": "7600.T",
      "name": "日本エム・ディ・エム",
      "market": "JP",
      "currency": "JPY",
      "price": 944.0,
      "day_chg": 0.0,
      "ret_1m": 15.54,
      "ret_3m": 71.32,
      "ret_6m": 92.97,
      "ret_1y": 73.05,
      "ytd_chg": 95.69,
      "rsi": 58.0,
      "from_ath": 0.0,
      "vol_ratio": 1.02,
      "volatility": 0.041,
      "score": 46.21,
      "ma5": 905.8,
      "ma20": 898.05,
      "ma50": 782.4,
      "high_52w": 944.0,
      "low_52w": 446.0
    },
    {
      "rank": 29,
      "ticker": "8362.T",
      "name": "福井銀行",
      "market": "JP",
      "currency": "JPY",
      "price": 5810.0,
      "day_chg": 0.87,
      "ret_1m": 6.61,
      "ret_3m": 63.43,
      "ret_6m": 119.76,
      "ret_1y": 232.85,
      "ytd_chg": 127.67,
      "rsi": 70.6,
      "from_ath": -4.6,
      "vol_ratio": 0.64,
      "volatility": 0.025,
      "score": 45.62,
      "ma5": 5930.0,
      "ma20": 5550.0,
      "ma50": 5056.1,
      "high_52w": 6090.0,
      "low_52w": 1742.66
    },
    {
      "rank": 30,
      "ticker": "HUM",
      "name": "Humana Inc.",
      "market": "US",
      "currency": "USD",
      "price": 406.0,
      "day_chg": 3.51,
      "ret_1m": 10.38,
      "ret_3m": 105.3,
      "ret_6m": 47.74,
      "ret_1y": 81.07,
      "ytd_chg": 54.65,
      "rsi": 74.7,
      "from_ath": -0.84,
      "vol_ratio": 0.73,
      "volatility": 0.02,
      "score": 45.29,
      "ma5": 397.38,
      "ma20": 382.86,
      "ma50": 334.32,
      "high_52w": 409.42,
      "low_52w": 162.46
    },
    {
      "rank": 31,
      "ticker": "DVA",
      "name": "DaVita Inc.",
      "market": "US",
      "currency": "USD",
      "price": 235.58,
      "day_chg": 1.19,
      "ret_1m": 15.58,
      "ret_3m": 55.44,
      "ret_6m": 111.38,
      "ret_1y": 64.27,
      "ytd_chg": 105.73,
      "rsi": 83.8,
      "from_ath": -0.06,
      "vol_ratio": 0.54,
      "volatility": 0.012,
      "score": 45.14,
      "ma5": 232.58,
      "ma20": 220.68,
      "ma50": 202.6,
      "high_52w": 235.71,
      "low_52w": 103.87
    },
    {
      "rank": 32,
      "ticker": "6752.T",
      "name": "パナソニック　ホールディングス",
      "market": "JP",
      "currency": "JPY",
      "price": 4419.0,
      "day_chg": -1.36,
      "ret_1m": 10.2,
      "ret_3m": 54.46,
      "ret_6m": 116.03,
      "ret_1y": 213.82,
      "ytd_chg": 114.21,
      "rsi": 55.6,
      "from_ath": -7.36,
      "vol_ratio": 0.66,
      "volatility": 0.03,
      "score": 43.62,
      "ma5": 4417.4,
      "ma20": 4430.4,
      "ma50": 3895.98,
      "high_52w": 4770.0,
      "low_52w": 1395.37
    },
    {
      "rank": 33,
      "ticker": "4047.T",
      "name": "関東電化工業",
      "market": "JP",
      "currency": "JPY",
      "price": 2935.0,
      "day_chg": -4.4,
      "ret_1m": -24.45,
      "ret_3m": 80.62,
      "ret_6m": 145.16,
      "ret_1y": 246.63,
      "ytd_chg": 160.03,
      "rsi": 30.1,
      "from_ath": -33.37,
      "vol_ratio": 0.71,
      "volatility": 0.041,
      "score": 43.43,
      "ma5": 3062.0,
      "ma20": 3548.0,
      "ma50": 3243.78,
      "high_52w": 4405.0,
      "low_52w": 793.63
    },
    {
      "rank": 34,
      "ticker": "MRVL",
      "name": "Marvell Technology, Inc.",
      "market": "US",
      "currency": "USD",
      "price": 217.53,
      "day_chg": -7.75,
      "ret_1m": -22.49,
      "ret_3m": 65.71,
      "ret_6m": 161.59,
      "ret_1y": 200.64,
      "ytd_chg": 143.71,
      "rsi": 26.8,
      "from_ath": -31.24,
      "vol_ratio": 0.52,
      "volatility": 0.063,
      "score": 43.04,
      "ma5": 231.77,
      "ma20": 268.95,
      "ma50": 232.63,
      "high_52w": 316.35,
      "low_52w": 62.18
    },
    {
      "rank": 35,
      "ticker": "MRNA",
      "name": "Moderna, Inc.",
      "market": "US",
      "currency": "USD",
      "price": 67.01,
      "day_chg": -1.85,
      "ret_1m": 34.99,
      "ret_3m": 32.22,
      "ret_6m": 95.36,
      "ret_1y": 103.86,
      "ytd_chg": 117.14,
      "rsi": 58.5,
      "from_ath": -18.08,
      "vol_ratio": 0.82,
      "volatility": 0.061,
      "score": 42.74,
      "ma5": 73.08,
      "ma20": 66.51,
      "ma50": 55.58,
      "high_52w": 81.8,
      "low_52w": 22.36
    },
    {
      "rank": 36,
      "ticker": "6387.T",
      "name": "サムコ",
      "market": "JP",
      "currency": "JPY",
      "price": 12920.0,
      "day_chg": -0.46,
      "ret_1m": -15.0,
      "ret_3m": 40.13,
      "ret_6m": 183.02,
      "ret_1y": 353.54,
      "ytd_chg": 183.02,
      "rsi": 37.8,
      "from_ath": -20.35,
      "vol_ratio": 0.67,
      "volatility": 0.052,
      "score": 42.64,
      "ma5": 12116.0,
      "ma20": 13795.5,
      "ma50": 12736.0,
      "high_52w": 16220.0,
      "low_52w": 2766.0
    },
    {
      "rank": 37,
      "ticker": "7236.T",
      "name": "ティラド",
      "market": "JP",
      "currency": "JPY",
      "price": 1468.0,
      "day_chg": -0.68,
      "ret_1m": 1.94,
      "ret_3m": 79.02,
      "ret_6m": 88.51,
      "ret_1y": 236.38,
      "ytd_chg": 88.28,
      "rsi": 51.3,
      "from_ath": -5.84,
      "vol_ratio": 0.75,
      "volatility": 0.021,
      "score": 42.19,
      "ma5": 1481.6,
      "ma20": 1475.15,
      "ma50": 1453.74,
      "high_52w": 1559.0,
      "low_52w": 418.25
    },
    {
      "rank": 38,
      "ticker": "CRWD",
      "name": "CrowdStrike Holdings, Inc.",
      "market": "US",
      "currency": "USD",
      "price": 187.91,
      "day_chg": 0.39,
      "ret_1m": 8.69,
      "ret_3m": 86.86,
      "ret_6m": 59.72,
      "ret_1y": 57.85,
      "ytd_chg": 65.71,
      "rsi": 65.4,
      "from_ath": -5.75,
      "vol_ratio": 0.56,
      "volatility": 0.026,
      "score": 41.48,
      "ma5": 191.85,
      "ma20": 181.52,
      "ma50": 164.72,
      "high_52w": 199.38,
      "low_52w": 87.56
    },
    {
      "rank": 39,
      "ticker": "4968.T",
      "name": "荒川化学工業",
      "market": "JP",
      "currency": "JPY",
      "price": 2176.0,
      "day_chg": -4.23,
      "ret_1m": 14.29,
      "ret_3m": 69.08,
      "ret_6m": 71.69,
      "ret_1y": 115.79,
      "ytd_chg": 75.35,
      "rsi": 41.0,
      "from_ath": -8.92,
      "vol_ratio": 1.07,
      "volatility": 0.052,
      "score": 40.77,
      "ma5": 2134.8,
      "ma20": 2119.75,
      "ma50": 1715.26,
      "high_52w": 2389.0,
      "low_52w": 992.08
    },
    {
      "rank": 40,
      "ticker": "2371.T",
      "name": "カカクコム",
      "market": "JP",
      "currency": "JPY",
      "price": 3640.0,
      "day_chg": 0.28,
      "ret_1m": 9.47,
      "ret_3m": 82.91,
      "ret_6m": 60.33,
      "ret_1y": 44.14,
      "ytd_chg": 61.74,
      "rsi": 88.5,
      "from_ath": -0.27,
      "vol_ratio": 0.48,
      "volatility": 0.011,
      "score": 40.73,
      "ma5": 3625.0,
      "ma20": 3441.7,
      "ma50": 3326.27,
      "high_52w": 3650.0,
      "low_52w": 1552.89
    },
    {
      "rank": 41,
      "ticker": "6058.T",
      "name": "ベクトル",
      "market": "JP",
      "currency": "JPY",
      "price": 1948.0,
      "day_chg": -1.72,
      "ret_1m": 30.56,
      "ret_3m": 51.95,
      "ret_6m": 58.42,
      "ret_1y": 86.9,
      "ytd_chg": 67.04,
      "rsi": 89.2,
      "from_ath": -1.72,
      "vol_ratio": 0.99,
      "volatility": 0.021,
      "score": 39.49,
      "ma5": 1926.8,
      "ma20": 1746.8,
      "ma50": 1502.94,
      "high_52w": 1982.0,
      "low_52w": 1035.44
    },
    {
      "rank": 42,
      "ticker": "8366.T",
      "name": "滋賀銀行",
      "market": "JP",
      "currency": "JPY",
      "price": 2867.0,
      "day_chg": -0.73,
      "ret_1m": 25.58,
      "ret_3m": 37.18,
      "ret_6m": 88.85,
      "ret_1y": 139.93,
      "ytd_chg": 96.3,
      "rsi": 81.1,
      "from_ath": -0.83,
      "vol_ratio": 0.93,
      "volatility": 0.022,
      "score": 39.16,
      "ma5": 2848.0,
      "ma20": 2540.55,
      "ma50": 2253.82,
      "high_52w": 2891.0,
      "low_52w": 1169.41
    },
    {
      "rank": 43,
      "ticker": "3687.T",
      "name": "フィックスターズ",
      "market": "JP",
      "currency": "JPY",
      "price": 2279.0,
      "day_chg": -2.15,
      "ret_1m": 7.15,
      "ret_3m": 90.39,
      "ret_6m": 45.07,
      "ret_1y": 22.27,
      "ytd_chg": 46.18,
      "rsi": 33.3,
      "from_ath": -37.3,
      "vol_ratio": 0.22,
      "volatility": 0.064,
      "score": 38.99,
      "ma5": 2258.4,
      "ma20": 2440.35,
      "ma50": 2208.34,
      "high_52w": 3635.0,
      "low_52w": 1195.0
    },
    {
      "rank": 44,
      "ticker": "9304.T",
      "name": "澁澤倉庫",
      "market": "JP",
      "currency": "JPY",
      "price": 1977.0,
      "day_chg": 5.78,
      "ret_1m": 33.13,
      "ret_3m": 48.31,
      "ret_6m": 54.93,
      "ret_1y": 99.62,
      "ytd_chg": 57.58,
      "rsi": 80.3,
      "from_ath": 0.0,
      "vol_ratio": 1.72,
      "volatility": 0.029,
      "score": 38.73,
      "ma5": 1874.4,
      "ma20": 1673.05,
      "ma50": 1508.74,
      "high_52w": 1977.0,
      "low_52w": 988.02
    },
    {
      "rank": 45,
      "ticker": "4413.T",
      "name": "ボードルア",
      "market": "JP",
      "currency": "JPY",
      "price": 3160.0,
      "day_chg": -1.25,
      "ret_1m": 29.35,
      "ret_3m": 66.05,
      "ret_6m": 35.5,
      "ret_1y": 10.72,
      "ytd_chg": 41.42,
      "rsi": 89.3,
      "from_ath": -6.39,
      "vol_ratio": 0.95,
      "volatility": 0.029,
      "score": 38.66,
      "ma5": 3118.2,
      "ma20": 2713.05,
      "ma50": 2457.88,
      "high_52w": 3375.73,
      "low_52w": 1704.79
    },
    {
      "rank": 46,
      "ticker": "6963.T",
      "name": "ローム",
      "market": "JP",
      "currency": "JPY",
      "price": 5243.0,
      "day_chg": -6.38,
      "ret_1m": -0.27,
      "ret_3m": 43.6,
      "ret_6m": 127.16,
      "ret_1y": 178.6,
      "ytd_chg": 132.0,
      "rsi": 47.0,
      "from_ath": -11.88,
      "vol_ratio": 0.87,
      "volatility": 0.053,
      "score": 38.41,
      "ma5": 5418.4,
      "ma20": 5429.0,
      "ma50": 4945.7,
      "high_52w": 5950.0,
      "low_52w": 1842.18
    },
    {
      "rank": 47,
      "ticker": "6723.T",
      "name": "ルネサスエレクトロニクス",
      "market": "JP",
      "currency": "JPY",
      "price": 4469.0,
      "day_chg": -6.15,
      "ret_1m": -0.42,
      "ret_3m": 68.23,
      "ret_6m": 90.21,
      "ret_1y": 134.47,
      "ytd_chg": 100.85,
      "rsi": 41.1,
      "from_ath": -12.77,
      "vol_ratio": 0.76,
      "volatility": 0.035,
      "score": 38.34,
      "ma5": 4690.8,
      "ma20": 4747.65,
      "ma50": 4332.04,
      "high_52w": 5123.0,
      "low_52w": 1640.97
    },
    {
      "rank": 48,
      "ticker": "2175.T",
      "name": "エス・エム・エス",
      "market": "JP",
      "currency": "JPY",
      "price": 2441.0,
      "day_chg": 4.18,
      "ret_1m": 21.56,
      "ret_3m": 43.59,
      "ret_6m": 81.75,
      "ret_1y": 72.36,
      "ytd_chg": 84.04,
      "rsi": 82.4,
      "from_ath": 0.0,
      "vol_ratio": 1.77,
      "volatility": 0.018,
      "score": 38.05,
      "ma5": 2372.0,
      "ma20": 2180.55,
      "ma50": 2022.74,
      "high_52w": 2441.0,
      "low_52w": 1267.39
    },
    {
      "rank": 49,
      "ticker": "INTC",
      "name": "Intel Corporation",
      "market": "US",
      "currency": "USD",
      "price": 103.12,
      "day_chg": -6.12,
      "ret_1m": -11.83,
      "ret_3m": 58.21,
      "ret_6m": 126.39,
      "ret_1y": 342.58,
      "ytd_chg": 161.86,
      "rsi": 23.4,
      "from_ath": -26.83,
      "vol_ratio": 0.82,
      "volatility": 0.057,
      "score": 38.01,
      "ma5": 109.23,
      "ma20": 123.88,
      "ma50": 117.17,
      "high_52w": 140.94,
      "low_52w": 19.31
    },
    {
      "rank": 50,
      "ticker": "5801.T",
      "name": "古河電気工業",
      "market": "JP",
      "currency": "JPY",
      "price": 3589.0,
      "day_chg": -3.65,
      "ret_1m": -18.38,
      "ret_3m": -21.64,
      "ret_6m": 257.07,
      "ret_1y": 402.37,
      "ytd_chg": 242.84,
      "rsi": 26.0,
      "from_ath": -40.32,
      "vol_ratio": 0.59,
      "volatility": 0.071,
      "score": 37.57,
      "ma5": 3614.4,
      "ma20": 4389.4,
      "ma50": 4739.0,
      "high_52w": 6014.0,
      "low_52w": 714.41
    }
  ],
  "deck": {
    "budget_man": 3000,
    "usdjpy": 162.44,
    "stocks": [
      {
        "ticker": "DELL",
        "name": "Dell Technologies Inc.",
        "market": "US",
        "currency": "USD",
        "price": 427.11,
        "ret_1m": 9.11,
        "ret_3m": 125.74,
        "rsi": 52.1,
        "score": 92.71,
        "shares": 27,
        "alloc_man": 186,
        "entry_price": 423.9,
        "stop_price": 394.23,
        "target_price": 456.64
      },
      {
        "ticker": "SNDK",
        "name": "Sandisk Corporation",
        "market": "US",
        "currency": "USD",
        "price": 1673.97,
        "ret_1m": -11.03,
        "ret_3m": 75.74,
        "rsi": 37.9,
        "score": 87.02,
        "shares": 7,
        "alloc_man": 181,
        "entry_price": 1590.27,
        "stop_price": 1478.95,
        "target_price": 1828.81
      },
      {
        "ticker": "AMD",
        "name": "Advanced Micro Devices, Inc.",
        "market": "US",
        "currency": "USD",
        "price": 534.39,
        "ret_1m": 9.41,
        "ret_3m": 116.5,
        "rsi": 47.3,
        "score": 71.32,
        "shares": 21,
        "alloc_man": 182,
        "entry_price": 533.25,
        "stop_price": 495.92,
        "target_price": 569.29
      },
      {
        "ticker": "MU",
        "name": "Micron Technology, Inc.",
        "market": "US",
        "currency": "USD",
        "price": 937.0,
        "ret_1m": -5.9,
        "ret_3m": 119.7,
        "rsi": 32.3,
        "score": 67.89,
        "shares": 12,
        "alloc_man": 174,
        "entry_price": 890.15,
        "stop_price": 827.84,
        "target_price": 1023.67
      },
      {
        "ticker": "DDOG",
        "name": "Datadog, Inc.",
        "market": "US",
        "currency": "USD",
        "price": 260.24,
        "ret_1m": 11.1,
        "ret_3m": 136.41,
        "rsi": 72.9,
        "score": 66.84,
        "shares": 44,
        "alloc_man": 185,
        "entry_price": 259.38,
        "stop_price": 241.22,
        "target_price": 298.29
      },
      {
        "ticker": "STX",
        "name": "Seagate Technology Holdings PLC",
        "market": "US",
        "currency": "USD",
        "price": 860.66,
        "ret_1m": -0.79,
        "ret_3m": 67.8,
        "rsi": 33.3,
        "score": 56.79,
        "shares": 14,
        "alloc_man": 186,
        "entry_price": 817.63,
        "stop_price": 760.39,
        "target_price": 940.27
      },
      {
        "ticker": "FTNT",
        "name": "Fortinet, Inc.",
        "market": "US",
        "currency": "USD",
        "price": 160.62,
        "ret_1m": 10.73,
        "ret_3m": 103.99,
        "rsi": 64.2,
        "score": 56.04,
        "shares": 72,
        "alloc_man": 186,
        "entry_price": 159.45,
        "stop_price": 148.29,
        "target_price": 183.37
      },
      {
        "ticker": "WDC",
        "name": "Western Digital Corporation",
        "market": "US",
        "currency": "USD",
        "price": 555.55,
        "ret_1m": 4.96,
        "ret_3m": 58.7,
        "rsi": 33.9,
        "score": 55.06,
        "shares": 21,
        "alloc_man": 180,
        "entry_price": 527.77,
        "stop_price": 490.83,
        "target_price": 606.94
      },
      {
        "ticker": "PANW",
        "name": "Palo Alto Networks, Inc.",
        "market": "US",
        "currency": "USD",
        "price": 330.3,
        "ret_1m": 18.16,
        "ret_3m": 103.25,
        "rsi": 63.6,
        "score": 53.19,
        "shares": 36,
        "alloc_man": 183,
        "entry_price": 312.83,
        "stop_price": 290.93,
        "target_price": 350.38
      },
      {
        "ticker": "HPE",
        "name": "Hewlett Packard Enterprise Comp",
        "market": "US",
        "currency": "USD",
        "price": 47.24,
        "ret_1m": 1.24,
        "ret_3m": 90.96,
        "rsi": 47.2,
        "score": 50.8,
        "shares": 247,
        "alloc_man": 187,
        "entry_price": 46.61,
        "stop_price": 43.35,
        "target_price": 53.6
      },
      {
        "ticker": "285A.T",
        "name": "キオクシアホールディングス",
        "market": "JP",
        "currency": "JPY",
        "price": 67100.0,
        "ret_1m": -26.19,
        "ret_3m": 122.63,
        "rsi": 33.6,
        "score": 112.06,
        "shares": 0,
        "alloc_man": 0,
        "entry_price": 63745.0,
        "stop_price": 59282.85,
        "target_price": 73306.75
      },
      {
        "ticker": "4392.T",
        "name": "ＦＩＧ",
        "market": "JP",
        "currency": "JPY",
        "price": 1051.0,
        "ret_1m": -20.2,
        "ret_3m": 226.4,
        "rsi": 42.3,
        "score": 110.38,
        "shares": 1800,
        "alloc_man": 180,
        "entry_price": 998.45,
        "stop_price": 928.56,
        "target_price": 1148.22
      },
      {
        "ticker": "3436.T",
        "name": "ＳＵＭＣＯ",
        "market": "JP",
        "currency": "JPY",
        "price": 5133.0,
        "ret_1m": 19.55,
        "ret_3m": 153.08,
        "rsi": 69.3,
        "score": 99.89,
        "shares": 300,
        "alloc_man": 144,
        "entry_price": 4799.6,
        "stop_price": 4463.63,
        "target_price": 5519.54
      },
      {
        "ticker": "6976.T",
        "name": "太陽誘電",
        "market": "JP",
        "currency": "JPY",
        "price": 11900.0,
        "ret_1m": -38.29,
        "ret_3m": 140.06,
        "rsi": 38.0,
        "score": 73.06,
        "shares": 100,
        "alloc_man": 113,
        "entry_price": 11305.0,
        "stop_price": 10513.65,
        "target_price": 13000.75
      },
      {
        "ticker": "6779.T",
        "name": "日本電波工業",
        "market": "JP",
        "currency": "JPY",
        "price": 3200.0,
        "ret_1m": -16.23,
        "ret_3m": 115.63,
        "rsi": 33.0,
        "score": 70.76,
        "shares": 600,
        "alloc_man": 182,
        "entry_price": 3040.0,
        "stop_price": 2827.2,
        "target_price": 3496.0
      },
      {
        "ticker": "6981.T",
        "name": "村田製作所",
        "market": "JP",
        "currency": "JPY",
        "price": 9066.0,
        "ret_1m": -9.88,
        "ret_3m": 118.67,
        "rsi": 37.8,
        "score": 66.43,
        "shares": 200,
        "alloc_man": 172,
        "entry_price": 8612.7,
        "stop_price": 8009.81,
        "target_price": 9904.6
      }
    ],
    "total_alloc_man": 2621,
    "remaining_man": 379,
    "max_loss_man": 183
  }
}